lohrasb/__init__.py
lohrasb/best_estimator.py
lohrasb/project_conf.py
lohrasb/tests_conf.py
lohrasb/version.py
lohrasb/abstracts/__init__.py
lohrasb/abstracts/estimators.py
lohrasb/abstracts/optimizers.py
lohrasb/base_classes/__init__.py
lohrasb/base_classes/optimizer_bases.py
lohrasb/decorators/__init__.py
lohrasb/decorators/decorators.py
lohrasb/factories/__init__.py
lohrasb/factories/factories.py
lohrasb/utils/__init__.py
lohrasb/utils/helper_funcs.py
lohrasb/utils/metrics.py
tests/__init__.py
tests/test_lohrasb.py
tests/test_optimize_by_gridsearchcv.py
tests/test_optimize_by_optunasearch.py
tests/test_optimize_by_optunasearchcv.py
tests/test_optimize_by_randomsearchcv.py
tests/test_optimize_by_tune.py
tests/test_optimize_by_tunegridsearchcv.py
tests/test_optimize_by_tunerandomsearchcv.py
lohrasb-4.2.0.dist-info/LICENSE
lohrasb-4.2.0.dist-info/METADATA
lohrasb-4.2.0.dist-info/WHEEL
lohrasb-4.2.0.dist-info/top_level.txt
lohrasb-4.2.0.dist-info/RECORD
