Metadata-Version: 2.1
Name: lohrasb
Version: 4.2.0
Summary: This versatile tool streamlines hyperparameter optimization in machine learning workflows.It supports a wide range of search methods, from GridSearchCV and RandomizedSearchCVto advanced techniques like OptunaSearchCV, Ray Tune, and Scikit-Learn Tune.Designed to enhance model performance and efficiency, it's suitable for tasks of any scale.
Home-page: 
Author: drhosseinjavedani
Author-email: h.javedani@gmail.com
License: BSD-3-Clause license
Keywords: Auto ML,Pipeline,Machine learning
License-File: LICENSE
Requires-Dist: aiosignal
Requires-Dist: alembic
Requires-Dist: ansi2html
Requires-Dist: appnope
Requires-Dist: argcomplete
Requires-Dist: astor
Requires-Dist: attrs
Requires-Dist: autograd
Requires-Dist: autograd-gamma
Requires-Dist: backcall
Requires-Dist: black
Requires-Dist: cached-property
Requires-Dist: catboost
Requires-Dist: certifi
Requires-Dist: charset-normalizer
Requires-Dist: click
Requires-Dist: cloudpickle
Requires-Dist: cmaes
Requires-Dist: colorlog
Requires-Dist: cycler
Requires-Dist: dash
Requires-Dist: dash-core-components
Requires-Dist: dash-cytoscape
Requires-Dist: dash-html-components
Requires-Dist: dash-table
Requires-Dist: debugpy
Requires-Dist: decorator
Requires-Dist: dill
Requires-Dist: distlib
Requires-Dist: entrypoints
Requires-Dist: exceptiongroup
Requires-Dist: filelock
Requires-Dist: Flask
Requires-Dist: fonttools
Requires-Dist: formulaic
Requires-Dist: frozenlist
Requires-Dist: future
Requires-Dist: gevent
Requires-Dist: graphlib-backport
Requires-Dist: graphviz
Requires-Dist: greenlet
Requires-Dist: grpcio
Requires-Dist: hyperopt
Requires-Dist: idna
Requires-Dist: imageio
Requires-Dist: imbalanced-learn
Requires-Dist: imblearn
Requires-Dist: importlib-metadata
Requires-Dist: importlib-resources
Requires-Dist: iniconfig
Requires-Dist: interface-meta
Requires-Dist: interpret
Requires-Dist: interpret-core
Requires-Dist: ipykernel
Requires-Dist: ipython
Requires-Dist: isort
Requires-Dist: itsdangerous
Requires-Dist: jedi
Requires-Dist: Jinja2
Requires-Dist: joblib
Requires-Dist: jsonschema
Requires-Dist: jupyter-client
Requires-Dist: jupyter-core
Requires-Dist: kiwisolver
Requires-Dist: lifelines
Requires-Dist: lightgbm
Requires-Dist: lime
Requires-Dist: llvmlite
Requires-Dist: Mako
Requires-Dist: MarkupSafe
Requires-Dist: matplotlib
Requires-Dist: matplotlib-inline
Requires-Dist: mccabe
Requires-Dist: msgpack
Requires-Dist: multiprocess
Requires-Dist: mypy-extensions
Requires-Dist: nest-asyncio
Requires-Dist: networkx
Requires-Dist: nox
Requires-Dist: numba
Requires-Dist: numpy
Requires-Dist: optuna
Requires-Dist: packaging
Requires-Dist: pandas
Requires-Dist: parso
Requires-Dist: pathos
Requires-Dist: pathspec
Requires-Dist: pexpect
Requires-Dist: pickleshare
Requires-Dist: Pillow
Requires-Dist: pkgutil-resolve-name
Requires-Dist: platformdirs
Requires-Dist: plotly
Requires-Dist: pluggy
Requires-Dist: pox
Requires-Dist: ppft
Requires-Dist: prompt-toolkit
Requires-Dist: protobuf
Requires-Dist: psutil
Requires-Dist: ptyprocess
Requires-Dist: py4j
Requires-Dist: pyarrow
Requires-Dist: pycodestyle
Requires-Dist: pyflakes
Requires-Dist: Pygments
Requires-Dist: pyparsing
Requires-Dist: pyrsistent
Requires-Dist: pytest
Requires-Dist: python-dateutil
Requires-Dist: python-dotenv
Requires-Dist: pytz
Requires-Dist: PyWavelets
Requires-Dist: PyYAML
Requires-Dist: pyzmq
Requires-Dist: ray
Requires-Dist: requests
Requires-Dist: retrying
Requires-Dist: ruamel.yaml
Requires-Dist: ruamel.yaml.clib
Requires-Dist: SALib
Requires-Dist: scikit-image
Requires-Dist: scikit-learn
Requires-Dist: scipy
Requires-Dist: shap
Requires-Dist: six
Requires-Dist: skope-rules
Requires-Dist: slicer
Requires-Dist: SQLAlchemy
Requires-Dist: tenacity
Requires-Dist: tensorboardX
Requires-Dist: threadpoolctl
Requires-Dist: tifffile
Requires-Dist: tomli
Requires-Dist: tornado
Requires-Dist: tqdm
Requires-Dist: traitlets
Requires-Dist: treeinterpreter
Requires-Dist: tune-sklearn
Requires-Dist: typed-ast
Requires-Dist: typing-extensions
Requires-Dist: urllib3
Requires-Dist: virtualenv
Requires-Dist: wcwidth
Requires-Dist: Werkzeug
Requires-Dist: wrapt
Requires-Dist: xgboost
Requires-Dist: xgbse
Requires-Dist: zipp
Requires-Dist: zope.event
Requires-Dist: zope.interface
